generate_synthetic_dataset/__init__.py
generate_synthetic_dataset-0.0.2.dist-info/METADATA
generate_synthetic_dataset-0.0.2.dist-info/WHEEL
generate_synthetic_dataset-0.0.2.dist-info/RECORD
