Metadata-Version: 2.4
Name: generate-synthetic-dataset
Version: 0.0.2
Summary: This is a placeholder for generate-synthetic-dataset. The functionality will be added soon.
License: MIT
Requires-Python: >=3.10
